config_tpg/__init__.py
config_tpg/__version__.py
config_tpg/config.py
config_tpg/configparms.py
config_tpg/configparms_ext.py
config_tpg/configutils.py
config_tpg/gen_config.py
config_tpg-0.1.5.dist-info/licenses/LICENSE
config_tpg-0.1.5.dist-info/METADATA
config_tpg-0.1.5.dist-info/WHEEL
config_tpg-0.1.5.dist-info/entry_points.txt
config_tpg-0.1.5.dist-info/top_level.txt
config_tpg-0.1.5.dist-info/RECORD
