Metadata-Version: 2.4
Name: config_tpg
Version: 0.1.5
Summary: Read a config file and create a config module which can be passed throughout an application. Reading and writing of the config file are based on configparser.
Author-email: Criss Swaim <cswaim@tpginc.net>
Maintainer-email: Criss Swaim <cswaim@tpginc.net>, Scott Allman <scott.m.allman@gmail.com>
Project-URL: Repository, https://gitlab.com/tpgllc/config_tpg
Project-URL: Customization, https://gitlab.com/tpgllc/config_tpg/-/blob/main/doc/customizing.md
Project-URL: Issues, https://gitlab.com/tpgllc/config_tpg/issues
Project-URL: Changelog, https://gitlab.com/tpgllc/config_tpg/-/blob/main/doc/changelog.md
Keywords: config,config file,config module,config generator,application config,application config file,app config,app config file,tpg
Classifier: Development Status :: 5 - Production/Stable
Classifier: Programming Language :: Python :: 3
Classifier: Operating System :: OS Independent
Classifier: License :: OSI Approved :: Apache Software License
Requires-Python: >=3.10
License-File: LICENSE
Dynamic: license-file
